etc/bash_completion.d/wo_auto.rc
etc/wo/wo.conf
etc/wo/plugins.d/clean.conf
etc/wo/plugins.d/debug.conf
etc/wo/plugins.d/import_slow_log.conf
etc/wo/plugins.d/info.conf
etc/wo/plugins.d/log.conf
etc/wo/plugins.d/maintenance.conf
etc/wo/plugins.d/secure.conf
etc/wo/plugins.d/site.conf
etc/wo/plugins.d/stack.conf
etc/wo/plugins.d/update.conf
tests/cli/13_test_stack_install.py
tests/cli/14_test_stack_services_stop.py
tests/cli/15_test_stack_services_start.py
tests/cli/16_test_stack_services_restart.py
tests/cli/17_test_stack_services_status.py
tests/cli/18_test_site_create.py
tests/cli/19_test_site_disable.py
tests/cli/20_test_site_enable.py
tests/cli/21_test_site_info.py
tests/cli/22_test_site_list.py
tests/cli/23_test_site_show.py
tests/cli/24_test_site_update.py
tests/cli/25_test_clean.py
tests/cli/27_test_info.py
tests/cli/28_test_secure.py
tests/cli/29_test_site_delete.py
tests/cli/30_test_stack_remove.py
tests/cli/31_test_stack_purge.py
tests/cli/__init__.py
tests/cli/ext/__init__.py
tests/cli/plugins/__init__.py
tests/core/__init__.py
usr/lib/wo/templates/22222.mustache
usr/lib/wo/templates/acl.mustache
usr/lib/wo/templates/anemometer.mustache
usr/lib/wo/templates/avif.mustache
usr/lib/wo/templates/blockips.mustache
usr/lib/wo/templates/brotli.mustache
usr/lib/wo/templates/cf-update.mustache
usr/lib/wo/templates/cloudflare.mustache
usr/lib/wo/templates/fail2ban-forbidden.mustache
usr/lib/wo/templates/fail2ban-wp.mustache
usr/lib/wo/templates/fail2ban.mustache
usr/lib/wo/templates/fastcgi.mustache
usr/lib/wo/templates/force-ssl.mustache
usr/lib/wo/templates/freshclam.mustache
usr/lib/wo/templates/gzip.mustache
usr/lib/wo/templates/info_mysql.mustache
usr/lib/wo/templates/info_nginx.mustache
usr/lib/wo/templates/info_php.mustache
usr/lib/wo/templates/locations.mustache
usr/lib/wo/templates/map-wp.mustache
usr/lib/wo/templates/mime.mustache
usr/lib/wo/templates/my.mustache
usr/lib/wo/templates/nextcloud.mustache
usr/lib/wo/templates/nginx-core.mustache
wordops-3.22.0.dist-info/LICENSE
wordops-3.22.0.dist-info/METADATA
wordops-3.22.0.dist-info/WHEEL
wordops-3.22.0.dist-info/entry_points.txt
wordops-3.22.0.dist-info/namespace_packages.txt
wordops-3.22.0.dist-info/top_level.txt
wordops-3.22.0.dist-info/RECORD
