Metadata-Version: 2.1
Name: wordops
Version: 3.22.0
Summary: An essential toolset that eases server administration
Home-page: https://github.com/WordOps/WordOps
Author: WordOps
Author-email: contact@wordops.io
License: MIT
Project-URL: Documentation, https://docs.wordops.net
Project-URL: Forum, https://community.wordops.net
Project-URL: Source, https://github.com/WordOps/WordOps
Project-URL: Tracker, https://github.com/WordOps/WordOps/issues
Keywords: nginx automation wordpress deployment CLI
Classifier: Programming Language :: Python :: 3
Classifier: License :: OSI Approved :: MIT License
Classifier: Operating System :: OS Independent
Classifier: Development Status :: 5 - Production/Stable
Classifier: Environment :: Console
Classifier: Natural Language :: English
Classifier: Topic :: System :: Systems Administration
Requires-Python: >=3.4
License-File: LICENSE
Requires-Dist: cement==2.10.14
Requires-Dist: pystache
Requires-Dist: pynginxconfig
Requires-Dist: PyMySQL>=1.0.2
Requires-Dist: psutil
Requires-Dist: sh
Requires-Dist: SQLAlchemy==1.4.54
Requires-Dist: requests
Requires-Dist: distro
Requires-Dist: argcomplete
Requires-Dist: colorlog
Provides-Extra: testing
Requires-Dist: nose; extra == "testing"
Requires-Dist: coverage; extra == "testing"
